packages/__init__.py
packages/main.py
packages/plots/__init__.py
packages/plots/plot_generator.py
packages/sequences/__init__.py
packages/sequences/sequences.py
packages/stats/__init__.py
packages/stats/sequence_stats.py
packages/transformers/__init__.py
packages/transformers/abstract_transformer.py
packages/transformers/duplicated_transformer.py
packages/transformers/reverse_complement.py
packages/utils/__init__.py
packages/utils/seq_file_manager.py
fasta_manager-1.3.2.dist-info/LICENSE
fasta_manager-1.3.2.dist-info/METADATA
fasta_manager-1.3.2.dist-info/WHEEL
fasta_manager-1.3.2.dist-info/entry_points.txt
fasta_manager-1.3.2.dist-info/top_level.txt
fasta_manager-1.3.2.dist-info/RECORD
