Metadata-Version: 2.1
Name: fasta_manager
Version: 1.3.2
Summary: Manage your fasta files
Home-page: https://github.com/santipvz/FASTA-manager
Author: santipvz
Author-email: santivzqzz@gmail.com
Project-URL: Bug Tracker, https://github.com/santipvz/FASTA-manager/issues
Classifier: Programming Language :: Python :: 3
Classifier: License :: OSI Approved :: MIT License
Classifier: Operating System :: OS Independent
Requires-Python: >=3.6
License-File: LICENSE
